{"total sales": "835223.09", "Total Pruchases": "10", "10001": {"name": "Renu", "phone number": "4785120369", "address": "West Delhi, 112973", "payment mode": "NEFT", "purchase time": "Fri Sep  3 19:05:52 2021", "bill": {"1": {"ID": "1006", "Quantity": "2"}, "2": {"ID": "1023", "Quantity": "1"}}, "Total Amount": "30888.2"}, "10002": {"name": "Arpit", "phone number": "4785123690", "address": "Anjkbdb msndbvks dnbv, 21344", "payment mode": "PhonePe", "purchase time": "Mon Sep  6 01:42:24 2021", "bill": {"1": {"ID": "1029", "Quantity": "2"}}, "Total Amount": "54114.34"}, "10003": {"name": "Aaruhi", "phone number": "8765439201", "address": "ghanitdha snhtiya, 2345", "payment mode": "Paytm", "purchase time": "Mon Sep  6 01:48:36 2021", "bill": {"1": {"ID": "1001", "Quantity": "1"}}, "Total Amount": "7199.1"}, "10004": {"name": "Annu", "phone number": "4587102693", "address": "qwery njkabjbf, 20291", "payment mode": "NEFT", "purchase time": "Mon Sep  6 01:50:21 2021", "bill": {"1": {"ID": "1003", "Quantity": "4"}}, "Total Amount": "35996.4"}, "10005": {"name": "Rahul Bali", "phone number": "478513558", "address": "Chetina chennai, 23124", "payment mode": "Paytm", "purchase time": "Mon Sep  6 01:52:16 2021", "bill": {"1": {"ID": "1001", "Quantity": "4"}}, "Total Amount": "28796.4"}, "10006": {"name": "Priya", "phone number": "4712589630", "address": "bhtiyhsna ajhtya, 29102", "payment mode": "NEFT", "purchase time": "Mon Sep  6 01:53:39 2021", "bill": {"1": {"ID": "1008", "Quantity": "2"}}, "Total Amount": "127398.18"}, "10007": {"name": "Raghav", "phone number": "9458720192", "address": "Jaipur rajasthan, 20192", "payment mode": "PhonePe", "purchase time": "Mon Sep  6 01:57:01 2021", "bill": {"1": {"ID": "1023", "Quantity": "1"}}, "Total Amount": "7490.0"}, "10008": {"name": "Nisha", "phone number": "7845123069", "address": "Ashok nagar, delhi, 11234", "payment mode": "NEFT", "purchase time": "Mon Sep  6 02:00:18 2021", "bill": {"1": {"ID": "1016", "Quantity": "3"}}, "Total Amount": "200637.36"}, "10009": {"name": "Harsh", "phone number": "8745112329", "address": "Rewari, haryana, 12329", "payment mode": "PhonePe", "purchase time": "Mon Sep  6 02:02:33 2021", "bill": {"1": {"ID": "1026", "Quantity": "2"}, "2": {"ID": "1029", "Quantity": "3"}}, "Total Amount": "142065.75"}, "10010": {"name": "Sanjay", "phone number": "784513690", "address": "Rewari, haryana, 12329", "payment mode": "NEFT", "purchase time": "Mon Sep  6 02:03:28 2021", "bill": {"1": {"ID": "1016", "Quantity": "3"}}, "Total Amount": "200637.36"}}
